acapy_agent/__init__.py
acapy_agent/__main__.py
acapy_agent/admin/__init__.py
acapy_agent/admin/base_server.py
acapy_agent/admin/decorators/auth.py
acapy_agent/admin/error.py
acapy_agent/admin/request_context.py
acapy_agent/admin/routes.py
acapy_agent/admin/server.py
acapy_agent/admin/tests/__init__.py
acapy_agent/admin/tests/test_admin_server.py
acapy_agent/admin/tests/test_auth.py
acapy_agent/admin/tests/test_request_context.py
acapy_agent/anoncreds/__init__.py
acapy_agent/anoncreds/base.py
acapy_agent/anoncreds/constants.py
acapy_agent/anoncreds/default/__init__.py
acapy_agent/anoncreds/default/did_web/__init__.py
acapy_agent/anoncreds/default/did_web/registry.py
acapy_agent/anoncreds/default/did_web/routes.py
acapy_agent/anoncreds/default/did_web/tests/__init__.py
acapy_agent/anoncreds/default/did_web/tests/test_registry.py
acapy_agent/anoncreds/default/legacy_indy/__init__.py
acapy_agent/anoncreds/default/legacy_indy/author.py
acapy_agent/anoncreds/default/legacy_indy/recover.py
acapy_agent/anoncreds/default/legacy_indy/registry.py
acapy_agent/anoncreds/default/legacy_indy/routes.py
acapy_agent/anoncreds/default/legacy_indy/tests/__init__.py
acapy_agent/anoncreds/default/legacy_indy/tests/test_recover.py
acapy_agent/anoncreds/default/legacy_indy/tests/test_registry.py
acapy_agent/anoncreds/error_messages.py
acapy_agent/anoncreds/events.py
acapy_agent/anoncreds/holder.py
acapy_agent/anoncreds/issuer.py
acapy_agent/anoncreds/models/__init__.py
acapy_agent/anoncreds/models/credential.py
acapy_agent/anoncreds/models/credential_definition.py
acapy_agent/anoncreds/models/credential_offer.py
acapy_agent/anoncreds/models/credential_proposal.py
acapy_agent/anoncreds/models/credential_request.py
acapy_agent/anoncreds/models/issuer_cred_rev_record.py
acapy_agent/anoncreds/models/non_rev_interval.py
acapy_agent/anoncreds/models/predicate.py
acapy_agent/anoncreds/models/presentation_request.py
acapy_agent/anoncreds/models/proof.py
acapy_agent-1.5.0.dist-info/METADATA
acapy_agent-1.5.0.dist-info/WHEEL
acapy_agent-1.5.0.dist-info/entry_points.txt
acapy_agent-1.5.0.dist-info/licenses/LICENSE
acapy_agent-1.5.0.dist-info/licenses/NOTICES
acapy_agent-1.5.0.dist-info/RECORD
