Metadata-Version: 2.4
Name: acapy_agent
Version: 1.5.0
Summary: (ACA-Py) A Cloud Agent Python is a foundation for building decentralized identity applications and services running in non-mobile environments. 
License: Apache-2.0
License-File: LICENSE
License-File: NOTICES
Requires-Python: >=3.13,<4.0
Classifier: License :: OSI Approved :: Apache Software License
Classifier: Operating System :: OS Independent
Classifier: Programming Language :: Python :: 3
Classifier: Programming Language :: Python :: 3.13
Classifier: Programming Language :: Python :: 3.14
Provides-Extra: bbs
Provides-Extra: didcommv2
Provides-Extra: sqlcipher
Requires-Dist: ConfigArgParse (>=1.7,<1.8)
Requires-Dist: Markdown (>=3.7,<3.11)
Requires-Dist: aiohttp (>=3.11.16,<3.14.0)
Requires-Dist: aiohttp-apispec-acapy (>=3.0.3,<3.1.0)
Requires-Dist: aiohttp-cors (>=0.7,<0.9)
Requires-Dist: anoncreds (>=0.2.3,<0.3.0)
Requires-Dist: apispec (>=6.6.0,<7.0.0)
Requires-Dist: aries-askar (>=0.4.3)
Requires-Dist: base58 (>=2.1.0,<2.2.0)
Requires-Dist: canonicaljson (>=2.0.0,<3.0.0)
Requires-Dist: deepmerge (>=2.0,<3.0)
Requires-Dist: did-peer-2 (>=0.1.2,<0.2.0)
Requires-Dist: did-peer-4 (>=0.1.4,<0.2.0)
Requires-Dist: did-webvh (>=1.0.0)
Requires-Dist: didcomm-messaging (>=0.1.1a0,<0.2.0) ; extra == "didcommv2"
Requires-Dist: indy-credx (>=1.1.1,<1.2.0)
Requires-Dist: indy-vdr (>=0.4.0,<0.5.0)
Requires-Dist: jsonpath-ng (>=1.7.0,<2.0.0)
Requires-Dist: markupsafe (>=3.0.2,<4.0.0)
Requires-Dist: marshmallow (>=3.26.1,<3.27.0)
Requires-Dist: nest_asyncio (>=1.6.0,<1.7.0)
Requires-Dist: packaging (>=24.2,<27.0)
Requires-Dist: portalocker (>=3.1.1,<4.0.0)
Requires-Dist: prompt_toolkit (>=3.0,<3.1)
Requires-Dist: psycopg[binary,pool] (>=3.2.1,<4.0.0)
Requires-Dist: pydid (>=0.5.1,<0.6.0)
Requires-Dist: pyjwt (>=2.10.1,<2.11.0)
Requires-Dist: pyld (>=2.0.4,<3.0.0)
Requires-Dist: pynacl (>=1.5,<1.7)
Requires-Dist: python-dateutil (>=2.9.0,<3.0.0)
Requires-Dist: python-json-logger (>=3.2.1,<4.0.0)
Requires-Dist: pyyaml (>=6.0.2,<6.1.0)
Requires-Dist: qrcode[pil] (>=8.1,<9.0)
Requires-Dist: requests (>=2.32.3,<2.33.0)
Requires-Dist: rlp (>=4.1.0,<5.0.0)
Requires-Dist: sd-jwt (>=0.10.3,<0.11.0)
Requires-Dist: sqlcipher3-binary (>=0.5.4) ; extra == "sqlcipher"
Requires-Dist: unflatten (>=0.2,<0.3)
Requires-Dist: ursa-bbs-signatures (>=1.0.1,<1.1.0) ; extra == "bbs"
Requires-Dist: uuid_utils (>=0.10,<0.15)
Project-URL: Repository, https://github.com/openwallet-foundation/acapy
